infi.asi-0.4.23-py2.7-nspkg.pth
infi/asi/__init__.py
infi/asi/__version__.py
infi/asi/aix.py
infi/asi/errors.py
infi/asi/executers.py
infi/asi/linux.py
infi/asi/solaris.py
infi/asi/unix.py
infi/asi/win32.py
infi/asi/cdb/__init__.py
infi/asi/cdb/compare_and_write.py
infi/asi/cdb/control.py
infi/asi/cdb/log_sense.py
infi/asi/cdb/operation_code.py
infi/asi/cdb/read.py
infi/asi/cdb/read_capacity.py
infi/asi/cdb/receive_copy_operating_parameters.py
infi/asi/cdb/release.py
infi/asi/cdb/report_luns.py
infi/asi/cdb/reserve.py
infi/asi/cdb/rtpg.py
infi/asi/cdb/tur.py
infi/asi/cdb/unmap.py
infi/asi/cdb/write.py
infi/asi/cdb/write_same.py
infi/asi/cdb/diagnostic/__init__.py
infi/asi/cdb/diagnostic/ses_pages/__init__.py
infi/asi/cdb/diagnostic/ses_pages/configuration.py
infi/asi/cdb/diagnostic/ses_pages/element_descriptor.py
infi/asi/cdb/diagnostic/ses_pages/enclosure_status.py
infi/asi/cdb/diagnostic/ses_pages/supported_pages.py
infi/asi/cdb/diagnostic/ses_pages/unknown.py
infi/asi/cdb/diagnostic/ses_pages/vendor_0x80.py
infi/asi/cdb/inquiry/__init__.py
infi/asi/cdb/inquiry/standard.py
infi/asi/cdb/inquiry/vpd_pages/__init__.py
infi/asi/cdb/inquiry/vpd_pages/ata_information.py
infi/asi/cdb/inquiry/vpd_pages/block_limits.py
infi/asi/cdb/inquiry/vpd_pages/designators.py
infi/asi/cdb/inquiry/vpd_pages/device_identification.py
infi/asi/cdb/inquiry/vpd_pages/logical_block_provisioning.py
infi/asi/cdb/inquiry/vpd_pages/supported_pages.py
infi/asi/cdb/inquiry/vpd_pages/unit_serial_number.py
infi/asi/cdb/inquiry/vpd_pages/unknown.py
infi/asi/cdb/inquiry/vpd_pages/veritas.py
infi/asi/cdb/persist/__init__.py
infi/asi/cdb/persist/input.py
infi/asi/cdb/persist/output.py
infi/asi/cdb/persist/transport.py
infi/asi/coroutines/__init__.py
infi/asi/coroutines/sync_adapter.py
infi/asi/sense/__init__.py
infi/asi/sense/asc.py
infi.asi-0.4.23.dist-info/LICENSE
infi.asi-0.4.23.dist-info/METADATA
infi.asi-0.4.23.dist-info/WHEEL
infi.asi-0.4.23.dist-info/entry_points.txt
infi.asi-0.4.23.dist-info/namespace_packages.txt
infi.asi-0.4.23.dist-info/top_level.txt
infi.asi-0.4.23.dist-info/RECORD
