Metadata-Version: 2.1
Name: infi.asi
Version: 0.4.23
Summary: asynchronous SCSI interface
Home-page: https://github.com/Infinidat/infi.asi
Author: Arnon Yaari
Author-email: arnony@infinidat.com
License: BSD
Platform: UNKNOWN
Classifier: Intended Audience :: Developers
Classifier: Intended Audience :: System Administrators
Classifier: License :: OSI Approved :: BSD License
Classifier: Operating System :: OS Independent
Classifier: Programming Language :: Python
Classifier: Programming Language :: Python :: 2
Classifier: Programming Language :: Python :: 3
Classifier: Topic :: Software Development :: Libraries :: Python Modules
Requires-Dist: infi.exceptools (>=0.2.1)
Requires-Dist: infi.instruct (>=0.6.25)
Requires-Dist: infi.os-info
Requires-Dist: infi.pyutils
Requires-Dist: setuptools
Requires-Dist: six
